namecom/__init__.py
namecom/api.py
namecom/auth.py
namecom/data_models.py
namecom/exceptions.py
namecom/result_models.py
namecom/utils/__init__.py
namecom/utils/json_utils.py
namecom/utils/parse_utils.py
pynamecom-0.1.4.dist-info/LICENSE
pynamecom-0.1.4.dist-info/METADATA
pynamecom-0.1.4.dist-info/WHEEL
pynamecom-0.1.4.dist-info/top_level.txt
pynamecom-0.1.4.dist-info/zip-safe
pynamecom-0.1.4.dist-info/RECORD
