Metadata-Version: 2.1
Name: pynamecom
Version: 0.1.4
Summary: Python Library for Name.com v4 API
Home-page: https://github.com/CtheSky/namecom
Author: Tianhong Chu
Author-email: cthesky13@gmail.com
License: UNKNOWN
Keywords: name.com,namecom,api,domain name registrar
Platform: any
Classifier: Development Status :: 5 - Production/Stable
Classifier: License :: OSI Approved :: MIT License
Classifier: Operating System :: OS Independent
Classifier: Intended Audience :: Customer Service
Classifier: Intended Audience :: Developers
Classifier: Topic :: Internet :: Name Service (DNS)
Classifier: Topic :: Software Development :: Libraries
Classifier: Topic :: Software Development :: Libraries :: Python Modules
Classifier: Programming Language :: Python
Classifier: Programming Language :: Python :: 2
Classifier: Programming Language :: Python :: 2.7
Classifier: Programming Language :: Python :: 3
Classifier: Programming Language :: Python :: 3.4
Classifier: Programming Language :: Python :: 3.5
Classifier: Programming Language :: Python :: 3.6
Classifier: Programming Language :: Python :: 3.7
Requires-Python: >= 2.7, != 3.0.*, != 3.1.*, != 3.2.*
Requires-Dist: requests (>=2.18.0)
